{"cameraMode":{"drawMode":0,"name":"Shaded","section":"Shading Mode"},"sceneLighting":true,"audioPlay":false,"sceneViewState":{"showFog":true,"showMaterialUpdate":false,"showSkybox":true,"showFlares":true,"showImageEffects":true,"showParticleSystems":true},"in2DMode":false,"pivot":{"x":0.9951766133308411,"y":-0.4092867970466614,"z":1.9309345483779908},"rotation":{"x":0.13899630308151246,"y":0.28812375664711,"z":-0.042311523109674457,"w":0.9465075731277466},"size":4.666298866271973,"orthographic":false}